manimcs/__init__.py
manimcs/algorithms/__init__.py
manimcs/algorithms/array_sort.py
manimcs/engine/__init__.py
manimcs/engine/engine.py
manimcs/mobjs/__init__.py
manimcs/mobjs/sort_set.py
manimcs/mobjs/sortable_mobject.py
manimcs/mobjs/svg_mobject.py
manimcs/renderer/__init__.py
manimcs/renderer/renderer.py
manimcs/scene/__init__.py
manimcs/scene/array_sort_scene.py
manimcs-0.4.7.dist-info/METADATA
manimcs-0.4.7.dist-info/WHEEL
manimcs-0.4.7.dist-info/top_level.txt
manimcs-0.4.7.dist-info/RECORD
