Metadata-Version: 2.1
Name: manimcs
Version: 0.4.7
Summary: An Animation Library for Explanitory Computer Science Videos
Home-page: https://github.com/CadenScharpf/manim-cs
Author: Caden Scharpf
Author-email: caden.scharpf@icloud.com
Classifier: Development Status :: 3 - Alpha
Classifier: Intended Audience :: Developers
Classifier: License :: OSI Approved :: MIT License
Classifier: Programming Language :: Python :: 3
Classifier: Programming Language :: Python :: 3.6
Classifier: Programming Language :: Python :: 3.7
Classifier: Programming Language :: Python :: 3.8
Classifier: Programming Language :: Python :: 3.9
Requires-Dist: manim (==0.17.3)
